album/__init__.py
album/environments/__init__.py
album/environments/environment_api.py
album/environments/initialization.py
album/environments/api/__init__.py
album/environments/api/environment_api.py
album/environments/api/controller/__init__.py
album/environments/api/controller/conda_lock_manager.py
album/environments/api/controller/package_manager.py
album/environments/api/model/__init__.py
album/environments/api/model/environment.py
album/environments/controller/__init__.py
album/environments/controller/conda_lock_manager.py
album/environments/controller/conda_manager.py
album/environments/controller/mamba_manager.py
album/environments/controller/micromamba_manager.py
album/environments/controller/package_manager.py
album/environments/model/__init__.py
album/environments/model/environment.py
album/environments/model/environment_default_values.py
album/environments/utils/__init__.py
album/environments/utils/file_operations.py
album/environments/utils/subcommand.py
album/environments/utils/url_operations.py
album_environments-0.3.1.dist-info/licenses/LICENSE
album_environments-0.3.1.dist-info/METADATA
album_environments-0.3.1.dist-info/WHEEL
album_environments-0.3.1.dist-info/top_level.txt
album_environments-0.3.1.dist-info/RECORD
