Metadata-Version: 2.4
Name: album-environments
Version: 0.3.1
Summary: Album unifies computational tools across frameworks, languages, and environments.
Home-page: https://gitlab.com/album-app/album-environments
Author: Deborah Schmidt, Jan Philipp Albrecht, Lucas Rieckert
Maintainer: Deborah Schmidt, Jan Philipp Albrecht, Lucas Rieckert
Maintainer-email: album@kyleharrington.com
License: MIT
Project-URL: Source, https://gitlab.com/album-app/album-environments
Project-URL: Tracker, https://gitlab.com/album-app/album-environments/issues
Keywords: virtual,environments,imaging,data analysis,micromamba,mamba,conda
Platform: any
Classifier: Development Status :: 3 - Alpha
Classifier: License :: OSI Approved :: MIT License
Classifier: Operating System :: MacOS :: MacOS X
Classifier: Operating System :: Microsoft :: Windows
Classifier: Operating System :: POSIX
Classifier: Programming Language :: Python :: 3.8
Classifier: Programming Language :: Python :: 3.9
Classifier: Programming Language :: Python :: Implementation :: PyPy
Classifier: Topic :: Utilities
Requires-Python: >=3.7
License-File: LICENSE
Requires-Dist: pyyaml>=5.4.1
Requires-Dist: validators>=0.18.2
Requires-Dist: requests>=2.25.1
Requires-Dist: jsonschema>=4.0.0
Requires-Dist: pre-commit>=2.20.0
Requires-Dist: conda-lock>=1.4.0
Requires-Dist: album-solution-api>=0.7.0
Requires-Dist: pooch>=1.8.1
Dynamic: license-file
